Metadata-Version: 2.4
Name: ggx
Version: 0.8.3
Summary: ⚠️ This project is discontinued and no longer maintained.
Author-email: mst4ck <mst4ck@mailfence.com>
License: MIT
Classifier: Development Status :: 7 - Inactive
Classifier: Programming Language :: Python :: 3
Classifier: Operating System :: OS Independent
Requires-Python: >=3.12
License-File: LICENSE
Requires-Dist: websockets>=15.0.1
Requires-Dist: loguru>=0.7.3
Requires-Dist: aiohttp==3.12.13
Dynamic: license-file
